taworld/__init__.py
taworld/core.py
taworld/custom.py
taworld/candles/__init__.py
taworld/candles/cdl_doji.py
taworld/candles/cdl_inside.py
taworld/candles/cdl_pattern.py
taworld/candles/cdl_z.py
taworld/candles/ha.py
taworld/cycles/__init__.py
taworld/cycles/ebsw.py
taworld/momentum/__init__.py
taworld/momentum/ao.py
taworld/momentum/apo.py
taworld/momentum/bias.py
taworld/momentum/bop.py
taworld/momentum/brar.py
taworld/momentum/cci.py
taworld/momentum/cfo.py
taworld/momentum/cg.py
taworld/momentum/cmo.py
taworld/momentum/coppock.py
taworld/momentum/cti.py
taworld/momentum/dm.py
taworld/momentum/er.py
taworld/momentum/eri.py
taworld/momentum/fisher.py
taworld/momentum/inertia.py
taworld/momentum/kdj.py
taworld/momentum/kst.py
taworld/momentum/macd.py
taworld/momentum/mom.py
taworld/momentum/pgo.py
taworld/momentum/ppo.py
taworld/momentum/psl.py
taworld/momentum/pvo.py
taworld/momentum/qqe.py
taworld/momentum/roc.py
taworld/momentum/rsi.py
taworld/momentum/rsx.py
taworld/momentum/rvgi.py
taworld/momentum/slope.py
taworld/momentum/smi.py
taworld/momentum/squeeze.py
taworld/momentum/squeeze_pro.py
taworld/momentum/stc.py
taworld/momentum/stoch.py
taworld/momentum/stochrsi.py
taworld/momentum/td_seq.py
taworld/momentum/trix.py
taworld/momentum/tsi.py
taworld/momentum/uo.py
taworld/momentum/willr.py
taworld/overlap/__init__.py
taworld/overlap/alma.py
taworld/overlap/dema.py
taworld/overlap/ema.py
taworld/overlap/fwma.py
taworld/overlap/hilo.py
taworld/overlap/hl2.py
taworld/overlap/hlc3.py
taworld/overlap/hma.py
taworld/overlap/hwma.py
taworld/overlap/ichimoku.py
taworld/overlap/jma.py
taworld/overlap/kama.py
taworld/overlap/linreg.py
taworld/overlap/ma.py
taworld/overlap/mcgd.py
taworld/overlap/midpoint.py
taworld/overlap/midprice.py
taworld/overlap/ohlc4.py
taworld/overlap/pwma.py
taworld/overlap/rma.py
taworld/overlap/sinwma.py
taworld/overlap/sma.py
taworld/overlap/ssf.py
taworld/overlap/supertrend.py
taworld/overlap/swma.py
taworld/overlap/t3.py
taworld-1.0.5.dist-info/LICENSE.txt
taworld-1.0.5.dist-info/METADATA
taworld-1.0.5.dist-info/WHEEL
taworld-1.0.5.dist-info/top_level.txt
taworld-1.0.5.dist-info/RECORD
